triton_python_backend_utils/__init__.py
triton_python_backend_mock_utils-1.0.0.dist-info/LICENSE
triton_python_backend_mock_utils-1.0.0.dist-info/METADATA
triton_python_backend_mock_utils-1.0.0.dist-info/WHEEL
triton_python_backend_mock_utils-1.0.0.dist-info/RECORD
