Metadata-Version: 2.1
Name: triton_python_backend_mock_utils
Version: 1.0.0
Summary: Mock library for triton python backend utils.
Author: W.W. Grainger MLOps & Platform Team
Author-email: mlopsplatformteam@grainger.com
Requires-Python: >=3.10,<4.0
Classifier: Programming Language :: Python :: 3
Classifier: Programming Language :: Python :: 3.10
Classifier: Programming Language :: Python :: 3.11
Classifier: Programming Language :: Python :: 3.12
Requires-Dist: numpy (>=1.24.1,<2.0.0)
